ngscheck_client/__init__.py
ngscheck_client/api.py
ngscheck_client/cli.py
ngscheck_client/util.py
ngscheck_client-1.2.1.dist-info/LICENSE
ngscheck_client-1.2.1.dist-info/METADATA
ngscheck_client-1.2.1.dist-info/WHEEL
ngscheck_client-1.2.1.dist-info/entry_points.txt
ngscheck_client-1.2.1.dist-info/top_level.txt
ngscheck_client-1.2.1.dist-info/RECORD
