Metadata-Version: 2.1
Name: ngscheck-client
Version: 1.2.1
Summary: client for remote NGSCheck service
Home-page: UNKNOWN
License: UNKNOWN
Platform: UNKNOWN
Classifier: Programming Language :: Python :: 3
Classifier: License :: OSI Approved :: MIT License
Classifier: Operating System :: POSIX :: Linux
Requires-Python: >=3.6
Requires-Dist: boto3
Requires-Dist: lxml
Requires-Dist: requests
